pyproject.toml
setup.py
RistoCalculator/RistoCalculator.py
RistoCalculator/__init__.py
RistoCalculator.egg-info/PKG-INFO
RistoCalculator.egg-info/SOURCES.txt
RistoCalculator.egg-info/dependency_links.txt
RistoCalculator.egg-info/top_level.txt