Metadata-Version: 1.0
Name: RistoCalculator
Version: 1.0
Summary: Makes Standard Calculations
Home-page: UNKNOWN
Author: Risto Tammistu
Author-email: UNKNOWN
License: UNKNOWN
Platform: UNKNOWN
